ismrmrd/__init__.py
ismrmrd/acquisition.py
ismrmrd/constants.py
ismrmrd/decorators.py
ismrmrd/equality.py
ismrmrd/file.py
ismrmrd/flags.py
ismrmrd/hdf5.py
ismrmrd/image.py
ismrmrd/meta.py
ismrmrd/serialization.py
ismrmrd/waveform.py
ismrmrd/xsd/__init__.py
ismrmrd/xsd/pyxb_compat.py
ismrmrd/xsd/ismrmrdschema/__init__.py
ismrmrd/xsd/ismrmrdschema/ismrmrd.py
ismrmrd/xsd/ismrmrdschema/__pycache__/__init__.cpython-312.pyc
ismrmrd/xsd/ismrmrdschema/__pycache__/ismrmrd.cpython-312.pyc
ismrmrd-1.14.2.dist-info/licenses/LICENSE
ismrmrd-1.14.2.dist-info/METADATA
ismrmrd-1.14.2.dist-info/WHEEL
ismrmrd-1.14.2.dist-info/top_level.txt
ismrmrd-1.14.2.dist-info/RECORD
