Metadata-Version: 2.4
Name: ismrmrd
Version: 1.14.2
Summary: Python implementation of ISMRMRD
Author: ISMRMRD Developers
License-Expression: LicenseRef-IsmrmrdSoftwareLicense
Project-URL: Homepage, https://github.com/ismrmrd/ismrmrd-python
Project-URL: Documentation, https://github.com/ismrmrd/ismrmrd-python
Project-URL: Repository, https://github.com/ismrmrd/ismrmrd-python
Keywords: ismrmrd
Classifier: Development Status :: 5 - Production/Stable
Classifier: Programming Language :: Python :: 3
Classifier: Operating System :: OS Independent
Classifier: Intended Audience :: Science/Research
Classifier: Topic :: Scientific/Engineering :: Medical Science Apps.
Requires-Python: >=3.9
License-File: LICENSE
Requires-Dist: h5py>=2.3
Requires-Dist: numpy>=1.22.0
Requires-Dist: xsdata>=22.12
Dynamic: license-file
